cgc/.env
cgc/CHANGELOG.md
cgc/__init__.py
cgc/cgc.py
cgc/config.py
cgc/commands/__init__.py
cgc/commands/cgc_cmd.py
cgc/commands/cgc_cmd_responses.py
cgc/commands/cgc_helpers.py
cgc/commands/cgc_models.py
cgc/commands/exceptions.py
cgc/commands/auth/__init__.py
cgc/commands/auth/auth_cmd.py
cgc/commands/auth/auth_logic.py
cgc/commands/auth/auth_responses.py
cgc/commands/auth/auth_utils.py
cgc/commands/compute/__init__.py
cgc/commands/compute/compute_cmd.py
cgc/commands/compute/compute_models.py
cgc/commands/compute/compute_responses.py
cgc/commands/compute/compute_utils.py
cgc/commands/compute/billing/__init__.py
cgc/commands/compute/billing/billing_cmd.py
cgc/commands/compute/billing/billing_responses.py
cgc/commands/compute/billing/billing_utils.py
cgc/commands/db/__init__.py
cgc/commands/db/db_cmd.py
cgc/commands/db/db_models.py
cgc/commands/debug/__init__.py
cgc/commands/debug/debug_cmd.py
cgc/commands/jobs/__init__.py
cgc/commands/jobs/job_utils.py
cgc/commands/jobs/jobs_cmd.py
cgc/commands/jobs/jobs_responses.py
cgc/commands/resource/__init__.py
cgc/commands/resource/resource_cmd.py
cgc/commands/resource/resource_responses.py
cgc/commands/user/__init__.py
cgc/commands/user/keys_cmd.py
cgc/commands/user/keys_models.py
cgc/commands/user/keys_responses.py
cgc/commands/user/keys_utils.py
cgc/commands/user/secret_cmd.py
cgc/commands/user/secret_models.py
cgc/commands/user/secret_responses.py
cgc/commands/user/secret_utils.py
cgc/commands/volume/__init__.py
cgc/commands/volume/data_model.py
cgc/commands/volume/volume_cmd.py
cgc/commands/volume/volume_models.py
cgc/commands/volume/volume_responses.py
cgc/commands/volume/volume_utils.py
cgc/sdk/__init__.py
cgc/sdk/context.py
cgc/sdk/exceptions.py
cgc/sdk/job.py
cgc/sdk/resource.py
cgc/sdk/volume.py
cgc/sdk/examples/README.md
cgc/sdk/examples/basic_compute.py
cgc/sdk/examples/database_connection.py
cgc/sdk/examples/job_workflow.py
cgc/sdk/examples/port_management.py
cgc/sdk/examples/volume_workflow.py
cgcsdk-1.4.1.dist-info/licenses/LICENSE
cgcsdk-1.4.1.dist-info/METADATA
cgcsdk-1.4.1.dist-info/WHEEL
cgcsdk-1.4.1.dist-info/entry_points.txt
cgcsdk-1.4.1.dist-info/top_level.txt
cgcsdk-1.4.1.dist-info/RECORD
