Metadata-Version: 2.4
Name: cgcsdk
Version: 1.4.1
Summary: CGC Core REST API client
Home-page: https://cgc.comtegra.cloud/
Author: Comtegra AI Team
Author-email: ai@comtegra.pl
License: BSD 2-clause
Project-URL: Documentation, https://docs.cgc.comtegra.cloud/
Project-URL: GitHub, https://git.comtegra.pl/cgc/cgc-client
Project-URL: Changelog, https://git.comtegra.pl/cgc/cgc-client/-/blob/main/cgc/CHANGELOG.md
Keywords: cloud,sdk,orchestrator,kubernetes,jupyter-notebook,cgc-core,cgc-universe
Classifier: Development Status :: 5 - Production/Stable
Classifier: Intended Audience :: Science/Research
Classifier: License :: OSI Approved :: BSD License
Classifier: Operating System :: POSIX :: Linux
Classifier: Programming Language :: Python :: 3.11
Classifier: Programming Language :: Python :: 3.12
Classifier: Programming Language :: Python :: 3.13
License-File: LICENSE
Requires-Dist: click
Requires-Dist: python-dotenv
Requires-Dist: tabulate
Requires-Dist: pycryptodomex
Requires-Dist: paramiko>=2.11
Requires-Dist: statsd
Requires-Dist: requests
Requires-Dist: setuptools
Requires-Dist: colorama
Requires-Dist: psycopg2-binary
Dynamic: author
Dynamic: author-email
Dynamic: classifier
Dynamic: description
Dynamic: description-content-type
Dynamic: home-page
Dynamic: keywords
Dynamic: license
Dynamic: license-file
Dynamic: project-url
Dynamic: requires-dist
Dynamic: summary
